{
  "optimization_id": "opt_XRP_USD_20250129_010223",
  "symbol": "XRP/USD",
  "training_period": {
    "start": "2022-01-01",
    "end": "2023-12-31"
  },
  "volatility": 0.7594954605352754,
  "strategies": {
    "ema": {
      "best_parameters": {
        "short": 11,
        "medium": 15,
        "long": 30
      },
      "performance": {
        "sharpe_ratio": 0.2025597169328463,
        "returns": 0.1539502723487552,
        "volatility": 0.7600241285871939,
        "max_drawdown": 0.6587987164087838,
        "win_rate": 0.4815034033737792,
        "num_trades": 505
      },
      "weight": 0.11419786857953006
    },
    "macd": {
      "best_parameters": {
        "fast": 12,
        "slow": 29,
        "signal": 11
      },
      "performance": {
        "sharpe_ratio": 0.7106990733999563,
        "returns": 0.5401341359405198,
        "volatility": 0.7600039962857127,
        "max_drawdown": 0.43489996176752155,
        "win_rate": 0.4889020420242675,
        "num_trades": 727
      },
      "weight": 0.40067354266015637
    },
    "rsi": {
      "best_parameters": {
        "period": 12,
        "overbought": 70,
        "oversold": 30
      },
      "performance": {
        "sharpe_ratio": 1.9326424450993707,
        "returns": 0.9261437040399877,
        "volatility": 0.4792110958695043,
        "max_drawdown": 0.32765777587161926,
        "win_rate": 0.5570815450643777,
        "num_trades": 748
      },
      "weight": 1.0895732443674793
    },
    "stochastic": {
      "best_parameters": {
        "k_period": 10,
        "d_period": 3,
        "overbought": 80,
        "oversold": 20
      },
      "performance": {
        "sharpe_ratio": 0.710189909636048,
        "returns": 0.2705434034310771,
        "volatility": 0.38094515250114275,
        "max_drawdown": 0.35175094629085335,
        "win_rate": 0.5662211421628189,
        "num_trades": 744
      },
      "weight": 0.4003864894519633
    },
    "vwap": {
      "best_parameters": {
        "period": 12,
        "overbought": 1.01,
        "oversold": 0.99
      },
      "performance": {
        "sharpe_ratio": 1.3870500151196141,
        "returns": 0.7170056634604505,
        "volatility": 0.5169284853788193,
        "max_drawdown": 0.32550324627869565,
        "win_rate": 0.5527015057573074,
        "num_trades": 740
      },
      "weight": 0.781982507372766
    },
    "volume_rsi": {
      "best_parameters": {
        "period": 10,
        "overbought": 75,
        "oversold": 25
      },
      "performance": {
        "sharpe_ratio": 0.12753717648295196,
        "returns": 0.039337039250810474,
        "volatility": 0.30843586423656405,
        "max_drawdown": 0.30301653388271366,
        "win_rate": 0.4780976220275344,
        "num_trades": 564
      },
      "weight": 0.07190212318391505
    }
  },
  "market_conditions": {
    "high_volatility": {
      "ema": {
        "parameters": {
          "short": 11,
          "medium": 15,
          "long": 30
        },
        "sharpe_ratio": 1.277484160112097
      },
      "macd": {
        "parameters": {
          "fast": 12,
          "slow": 29,
          "signal": 11
        },
        "sharpe_ratio": 2.1716750670596654
      },
      "rsi": {
        "parameters": {
          "period": 12,
          "overbought": 70,
          "oversold": 30
        },
        "sharpe_ratio": 2.049240811380583
      },
      "stochastic": {
        "parameters": {
          "k_period": 10,
          "d_period": 3,
          "overbought": 80,
          "oversold": 20
        },
        "sharpe_ratio": -1.7152174745287165
      },
      "vwap": {
        "parameters": {
          "period": 12,
          "overbought": 1.01,
          "oversold": 0.99
        },
        "sharpe_ratio": 1.2233510270646866
      },
      "volume_rsi": {
        "parameters": {
          "period": 10,
          "overbought": 75,
          "oversold": 25
        },
        "sharpe_ratio": 0.7828345796724072
      }
    },
    "low_volatility": {
      "ema": {
        "parameters": {
          "short": 11,
          "medium": 15,
          "long": 30
        },
        "sharpe_ratio": -3.625823406029459
      },
      "macd": {
        "parameters": {
          "fast": 12,
          "slow": 29,
          "signal": 11
        },
        "sharpe_ratio": -2.651087454082929
      },
      "rsi": {
        "parameters": {
          "period": 12,
          "overbought": 70,
          "oversold": 30
        },
        "sharpe_ratio": 2.8722738617805277
      },
      "stochastic": {
        "parameters": {
          "k_period": 10,
          "d_period": 3,
          "overbought": 80,
          "oversold": 20
        },
        "sharpe_ratio": 4.001322879519563
      },
      "vwap": {
        "parameters": {
          "period": 12,
          "overbought": 1.01,
          "oversold": 0.99
        },
        "sharpe_ratio": 0.23942594327406486
      },
      "volume_rsi": {
        "parameters": {
          "period": 10,
          "overbought": 75,
          "oversold": 25
        },
        "sharpe_ratio": 1.004976394249661
      }
    },
    "strong_trend": {
      "ema": {
        "parameters": {
          "short": 11,
          "medium": 15,
          "long": 30
        },
        "sharpe_ratio": 14.475507590305682
      },
      "macd": {
        "parameters": {
          "fast": 12,
          "slow": 29,
          "signal": 11
        },
        "sharpe_ratio": 11.500810581528045
      },
      "rsi": {
        "parameters": {
          "period": 12,
          "overbought": 70,
          "oversold": 30
        },
        "sharpe_ratio": -4.013836874800842
      },
      "stochastic": {
        "parameters": {
          "k_period": 10,
          "d_period": 3,
          "overbought": 80,
          "oversold": 20
        },
        "sharpe_ratio": -5.304601803694776
      },
      "vwap": {
        "parameters": {
          "period": 12,
          "overbought": 1.01,
          "oversold": 0.99
        },
        "sharpe_ratio": -5.39843154713974
      },
      "volume_rsi": {
        "parameters": {
          "period": 10,
          "overbought": 75,
          "oversold": 25
        },
        "sharpe_ratio": 0.2926081391369478
      }
    },
    "weak_trend": {
      "ema": {
        "parameters": {
          "short": 11,
          "medium": 15,
          "long": 30
        },
        "sharpe_ratio": -30.22448836378347
      },
      "macd": {
        "parameters": {
          "fast": 12,
          "slow": 29,
          "signal": 11
        },
        "sharpe_ratio": -13.70812570275193
      },
      "rsi": {
        "parameters": {
          "period": 12,
          "overbought": 70,
          "oversold": 30
        },
        "sharpe_ratio": 13.174112170210023
      },
      "stochastic": {
        "parameters": {
          "k_period": 10,
          "d_period": 3,
          "overbought": 80,
          "oversold": 20
        },
        "sharpe_ratio": 10.043028221644269
      },
      "vwap": {
        "parameters": {
          "period": 12,
          "overbought": 1.01,
          "oversold": 0.99
        },
        "sharpe_ratio": 10.890532349026213
      },
      "volume_rsi": {
        "parameters": {
          "period": 10,
          "overbought": 75,
          "oversold": 25
        },
        "sharpe_ratio": 0.07040029476002718
      }
    },
    "high_volume": {
      "ema": {
        "parameters": {
          "short": 11,
          "medium": 15,
          "long": 30
        },
        "sharpe_ratio": 6.048162106771049
      },
      "macd": {
        "parameters": {
          "fast": 12,
          "slow": 29,
          "signal": 11
        },
        "sharpe_ratio": 7.164631320237429
      },
      "rsi": {
        "parameters": {
          "period": 12,
          "overbought": 70,
          "oversold": 30
        },
        "sharpe_ratio": -3.7647486396521934
      },
      "stochastic": {
        "parameters": {
          "k_period": 10,
          "d_period": 3,
          "overbought": 80,
          "oversold": 20
        },
        "sharpe_ratio": -5.164279825939385
      },
      "vwap": {
        "parameters": {
          "period": 12,
          "overbought": 1.01,
          "oversold": 0.99
        },
        "sharpe_ratio": -4.293255222096827
      },
      "volume_rsi": {
        "parameters": {
          "period": 10,
          "overbought": 75,
          "oversold": 25
        },
        "sharpe_ratio": 0.39543154827935006
      }
    },
    "low_volume": {
      "ema": {
        "parameters": {
          "short": 11,
          "medium": 15,
          "long": 30
        },
        "sharpe_ratio": -5.4049486626565635
      },
      "macd": {
        "parameters": {
          "fast": 12,
          "slow": 29,
          "signal": 11
        },
        "sharpe_ratio": -7.6393348894412565
      },
      "rsi": {
        "parameters": {
          "period": 12,
          "overbought": 70,
          "oversold": 30
        },
        "sharpe_ratio": 5.759257166828506
      },
      "stochastic": {
        "parameters": {
          "k_period": 10,
          "d_period": 3,
          "overbought": 80,
          "oversold": 20
        },
        "sharpe_ratio": 9.34324450601831
      },
      "vwap": {
        "parameters": {
          "period": 12,
          "overbought": 1.01,
          "oversold": 0.99
        },
        "sharpe_ratio": 6.213466017458134
      },
      "volume_rsi": {
        "parameters": {
          "period": 10,
          "overbought": 75,
          "oversold": 25
        },
        "sharpe_ratio": 1.219704560823126
      }
    }
  },
  "timestamp": "2025-01-29T01:02:23.001234"
}